{
    "/js//main.min.js": "/js//main.min.js",
    "/js//login.min.js": "/js//login.min.js",
    "/js/bundle/dashboard.83a3473b8a5941e0.js": "/js/bundle/dashboard.83a3473b8a5941e0.js",
    "/js/bundle/products.83a3473b8a5941e0.js": "/js/bundle/products.83a3473b8a5941e0.js",
    "/js/bundle/index_products.83a3473b8a5941e0.js": "/js/bundle/index_products.83a3473b8a5941e0.js",
    "/js/bundle/store_product.83a3473b8a5941e0.js": "/js/bundle/store_product.83a3473b8a5941e0.js",
    "/js/bundle/edit_product.83a3473b8a5941e0.js": "/js/bundle/edit_product.83a3473b8a5941e0.js",
    "/js/bundle/detail_product.83a3473b8a5941e0.js": "/js/bundle/detail_product.83a3473b8a5941e0.js",
    "/js/bundle/opening_stock_import.83a3473b8a5941e0.js": "/js/bundle/opening_stock_import.83a3473b8a5941e0.js",
    "/js/bundle/barcode.83a3473b8a5941e0.js": "/js/bundle/barcode.83a3473b8a5941e0.js",
    "/js/bundle/count_stock.83a3473b8a5941e0.js": "/js/bundle/count_stock.83a3473b8a5941e0.js",
    "/js/bundle/Categories.83a3473b8a5941e0.js": "/js/bundle/Categories.83a3473b8a5941e0.js",
    "/js/bundle/Brands.83a3473b8a5941e0.js": "/js/bundle/Brands.83a3473b8a5941e0.js",
    "/js/bundle/units.83a3473b8a5941e0.js": "/js/bundle/units.83a3473b8a5941e0.js",
    "/js/bundle/adjustments.83a3473b8a5941e0.js": "/js/bundle/adjustments.83a3473b8a5941e0.js",
    "/js/bundle/index_adjustment.83a3473b8a5941e0.js": "/js/bundle/index_adjustment.83a3473b8a5941e0.js",
    "/js/bundle/store_adjustment.83a3473b8a5941e0.js": "/js/bundle/store_adjustment.83a3473b8a5941e0.js",
    "/js/bundle/edit_adjustment.83a3473b8a5941e0.js": "/js/bundle/edit_adjustment.83a3473b8a5941e0.js",
    "/js/bundle/transfers.83a3473b8a5941e0.js": "/js/bundle/transfers.83a3473b8a5941e0.js",
    "/js/bundle/index_transfer.83a3473b8a5941e0.js": "/js/bundle/index_transfer.83a3473b8a5941e0.js",
    "/js/bundle/store_transfer.83a3473b8a5941e0.js": "/js/bundle/store_transfer.83a3473b8a5941e0.js",
    "/js/bundle/edit_transfer.83a3473b8a5941e0.js": "/js/bundle/edit_transfer.83a3473b8a5941e0.js",
    "/js/bundle/accounts.83a3473b8a5941e0.js": "/js/bundle/accounts.83a3473b8a5941e0.js",
    "/js/bundle/projects.83a3473b8a5941e0.js": "/js/bundle/projects.83a3473b8a5941e0.js",
    "/js/bundle/index_project.83a3473b8a5941e0.js": "/js/bundle/index_project.83a3473b8a5941e0.js",
    "/js/bundle/store_project.83a3473b8a5941e0.js": "/js/bundle/store_project.83a3473b8a5941e0.js",
    "/js/bundle/edit_project.83a3473b8a5941e0.js": "/js/bundle/edit_project.83a3473b8a5941e0.js",
    "/js/bundle/tasks.83a3473b8a5941e0.js": "/js/bundle/tasks.83a3473b8a5941e0.js",
    "/js/bundle/index_task.83a3473b8a5941e0.js": "/js/bundle/index_task.83a3473b8a5941e0.js",
    "/js/bundle/store_task.83a3473b8a5941e0.js": "/js/bundle/store_task.83a3473b8a5941e0.js",
    "/js/bundle/edit_task.83a3473b8a5941e0.js": "/js/bundle/edit_task.83a3473b8a5941e0.js",
    "/js/bundle/transfer_money.83a3473b8a5941e0.js": "/js/bundle/transfer_money.83a3473b8a5941e0.js",
    "/js/bundle/expenses.83a3473b8a5941e0.js": "/js/bundle/expenses.83a3473b8a5941e0.js",
    "/js/bundle/index_expense.83a3473b8a5941e0.js": "/js/bundle/index_expense.83a3473b8a5941e0.js",
    "/js/bundle/store_expense.83a3473b8a5941e0.js": "/js/bundle/store_expense.83a3473b8a5941e0.js",
    "/js/bundle/edit_expense.83a3473b8a5941e0.js": "/js/bundle/edit_expense.83a3473b8a5941e0.js",
    "/js/bundle/expense_category.83a3473b8a5941e0.js": "/js/bundle/expense_category.83a3473b8a5941e0.js",
    "/js/bundle/deposits.83a3473b8a5941e0.js": "/js/bundle/deposits.83a3473b8a5941e0.js",
    "/js/bundle/index_deposit.83a3473b8a5941e0.js": "/js/bundle/index_deposit.83a3473b8a5941e0.js",
    "/js/bundle/store_deposit.83a3473b8a5941e0.js": "/js/bundle/store_deposit.83a3473b8a5941e0.js",
    "/js/bundle/edit_deposit.83a3473b8a5941e0.js": "/js/bundle/edit_deposit.83a3473b8a5941e0.js",
    "/js/bundle/deposit_category.83a3473b8a5941e0.js": "/js/bundle/deposit_category.83a3473b8a5941e0.js",
    "/js/bundle/quotations.83a3473b8a5941e0.js": "/js/bundle/quotations.83a3473b8a5941e0.js",
    "/js/bundle/store_quotation.83a3473b8a5941e0.js": "/js/bundle/store_quotation.83a3473b8a5941e0.js",
    "/js/bundle/edit_quotation.83a3473b8a5941e0.js": "/js/bundle/edit_quotation.83a3473b8a5941e0.js",
    "/js/bundle/detail_quotation.83a3473b8a5941e0.js": "/js/bundle/detail_quotation.83a3473b8a5941e0.js",
    "/js/bundle/change_to_sale.83a3473b8a5941e0.js": "/js/bundle/change_to_sale.83a3473b8a5941e0.js",
    "/js/bundle/purchases.83a3473b8a5941e0.js": "/js/bundle/purchases.83a3473b8a5941e0.js",
    "/js/bundle/index_purchases.83a3473b8a5941e0.js": "/js/bundle/index_purchases.83a3473b8a5941e0.js",
    "/js/bundle/store_purchase.83a3473b8a5941e0.js": "/js/bundle/store_purchase.83a3473b8a5941e0.js",
    "/js/bundle/import_purchases.83a3473b8a5941e0.js": "/js/bundle/import_purchases.83a3473b8a5941e0.js",
    "/js/bundle/edit_purchase.83a3473b8a5941e0.js": "/js/bundle/edit_purchase.83a3473b8a5941e0.js",
    "/js/bundle/create_purchase_return.83a3473b8a5941e0.js": "/js/bundle/create_purchase_return.83a3473b8a5941e0.js",
    "/js/bundle/detail_purchase.83a3473b8a5941e0.js": "/js/bundle/detail_purchase.83a3473b8a5941e0.js",
    "/js/bundle/sales.83a3473b8a5941e0.js": "/js/bundle/sales.83a3473b8a5941e0.js",
    "/js/bundle/index_sales.83a3473b8a5941e0.js": "/js/bundle/index_sales.83a3473b8a5941e0.js",
    "/js/bundle/store_sale.83a3473b8a5941e0.js": "/js/bundle/store_sale.83a3473b8a5941e0.js",
    "/js/bundle/edit_sale.83a3473b8a5941e0.js": "/js/bundle/edit_sale.83a3473b8a5941e0.js",
    "/js/bundle/create_sale_return.83a3473b8a5941e0.js": "/js/bundle/create_sale_return.83a3473b8a5941e0.js",
    "/js/bundle/detail_sale.83a3473b8a5941e0.js": "/js/bundle/detail_sale.83a3473b8a5941e0.js",
    "/js/bundle/shipment.83a3473b8a5941e0.js": "/js/bundle/shipment.83a3473b8a5941e0.js",
    "/js/bundle/sale_return.83a3473b8a5941e0.js": "/js/bundle/sale_return.83a3473b8a5941e0.js",
    "/js/bundle/index_sale_return.83a3473b8a5941e0.js": "/js/bundle/index_sale_return.83a3473b8a5941e0.js",
    "/js/bundle/edit_sale_return.83a3473b8a5941e0.js": "/js/bundle/edit_sale_return.83a3473b8a5941e0.js",
    "/js/bundle/detail_sale_return.83a3473b8a5941e0.js": "/js/bundle/detail_sale_return.83a3473b8a5941e0.js",
    "/js/bundle/purchase_return.83a3473b8a5941e0.js": "/js/bundle/purchase_return.83a3473b8a5941e0.js",
    "/js/bundle/index_purchase_return.83a3473b8a5941e0.js": "/js/bundle/index_purchase_return.83a3473b8a5941e0.js",
    "/js/bundle/edit_purchase_return.83a3473b8a5941e0.js": "/js/bundle/edit_purchase_return.83a3473b8a5941e0.js",
    "/js/bundle/detail_purchase_return.83a3473b8a5941e0.js": "/js/bundle/detail_purchase_return.83a3473b8a5941e0.js",
    "/js/bundle/hrm.83a3473b8a5941e0.js": "/js/bundle/hrm.83a3473b8a5941e0.js",
    "/js/bundle/employees.83a3473b8a5941e0.js": "/js/bundle/employees.83a3473b8a5941e0.js",
    "/js/bundle/index_employee.83a3473b8a5941e0.js": "/js/bundle/index_employee.83a3473b8a5941e0.js",
    "/js/bundle/store_employee.83a3473b8a5941e0.js": "/js/bundle/store_employee.83a3473b8a5941e0.js",
    "/js/bundle/edit_employee.83a3473b8a5941e0.js": "/js/bundle/edit_employee.83a3473b8a5941e0.js",
    "/js/bundle/detail_employee.83a3473b8a5941e0.js": "/js/bundle/detail_employee.83a3473b8a5941e0.js",
    "/js/bundle/company.83a3473b8a5941e0.js": "/js/bundle/company.83a3473b8a5941e0.js",
    "/js/bundle/departments.83a3473b8a5941e0.js": "/js/bundle/departments.83a3473b8a5941e0.js",
    "/js/bundle/designations.83a3473b8a5941e0.js": "/js/bundle/designations.83a3473b8a5941e0.js",
    "/js/bundle/office_shift.83a3473b8a5941e0.js": "/js/bundle/office_shift.83a3473b8a5941e0.js",
    "/js/bundle/attendance.83a3473b8a5941e0.js": "/js/bundle/attendance.83a3473b8a5941e0.js",
    "/js/bundle/holidays.83a3473b8a5941e0.js": "/js/bundle/holidays.83a3473b8a5941e0.js",
    "/js/bundle/payrolls.83a3473b8a5941e0.js": "/js/bundle/payrolls.83a3473b8a5941e0.js",
    "/js/bundle/leaves.83a3473b8a5941e0.js": "/js/bundle/leaves.83a3473b8a5941e0.js",
    "/js/bundle/leave_list.83a3473b8a5941e0.js": "/js/bundle/leave_list.83a3473b8a5941e0.js",
    "/js/bundle/leave_type.83a3473b8a5941e0.js": "/js/bundle/leave_type.83a3473b8a5941e0.js",
    "/js/bundle/People.83a3473b8a5941e0.js": "/js/bundle/People.83a3473b8a5941e0.js",
    "/js/bundle/Customers.83a3473b8a5941e0.js": "/js/bundle/Customers.83a3473b8a5941e0.js",
    "/js/bundle/Customers_without_ecommerce.83a3473b8a5941e0.js": "/js/bundle/Customers_without_ecommerce.83a3473b8a5941e0.js",
    "/js/bundle/Suppliers.83a3473b8a5941e0.js": "/js/bundle/Suppliers.83a3473b8a5941e0.js",
    "/js/bundle/Users.83a3473b8a5941e0.js": "/js/bundle/Users.83a3473b8a5941e0.js",
    "/js/bundle/subscription_product.83a3473b8a5941e0.js": "/js/bundle/subscription_product.83a3473b8a5941e0.js",
    "/js/bundle/subscription_product_create.83a3473b8a5941e0.js": "/js/bundle/subscription_product_create.83a3473b8a5941e0.js",
    "/js/bundle/subscription_product_details.83a3473b8a5941e0.js": "/js/bundle/subscription_product_details.83a3473b8a5941e0.js",
    "/js/bundle/settings.83a3473b8a5941e0.js": "/js/bundle/settings.83a3473b8a5941e0.js",
    "/js/bundle/permissions.83a3473b8a5941e0.js": "/js/bundle/permissions.83a3473b8a5941e0.js",
    "/js/bundle/groupPermission.83a3473b8a5941e0.js": "/js/bundle/groupPermission.83a3473b8a5941e0.js",
    "/js/bundle/store_permission.83a3473b8a5941e0.js": "/js/bundle/store_permission.83a3473b8a5941e0.js",
    "/js/bundle/edit_permission.83a3473b8a5941e0.js": "/js/bundle/edit_permission.83a3473b8a5941e0.js",
    "/js/bundle/payment_methods.83a3473b8a5941e0.js": "/js/bundle/payment_methods.83a3473b8a5941e0.js",
    "/js/bundle/sms_settings.83a3473b8a5941e0.js": "/js/bundle/sms_settings.83a3473b8a5941e0.js",
    "/js/bundle/sms_templates.83a3473b8a5941e0.js": "/js/bundle/sms_templates.83a3473b8a5941e0.js",
    "/js/bundle/email_templates.83a3473b8a5941e0.js": "/js/bundle/email_templates.83a3473b8a5941e0.js",
    "/js/bundle/appearance_settings.83a3473b8a5941e0.js": "/js/bundle/appearance_settings.83a3473b8a5941e0.js",
    "/js/bundle/translations_settings.83a3473b8a5941e0.js": "/js/bundle/translations_settings.83a3473b8a5941e0.js",
    "/js/bundle/translations_view.83a3473b8a5941e0.js": "/js/bundle/translations_view.83a3473b8a5941e0.js",
    "/js/bundle/pos_settings.83a3473b8a5941e0.js": "/js/bundle/pos_settings.83a3473b8a5941e0.js",
    "/js/bundle/payment_gateway.83a3473b8a5941e0.js": "/js/bundle/payment_gateway.83a3473b8a5941e0.js",
    "/js/bundle/mail_settings.83a3473b8a5941e0.js": "/js/bundle/mail_settings.83a3473b8a5941e0.js",
    "/js/bundle/module_settings.83a3473b8a5941e0.js": "/js/bundle/module_settings.83a3473b8a5941e0.js",
    "/js/bundle/update_settings.83a3473b8a5941e0.js": "/js/bundle/update_settings.83a3473b8a5941e0.js",
    "/js/bundle/Currencies.83a3473b8a5941e0.js": "/js/bundle/Currencies.83a3473b8a5941e0.js",
    "/js/bundle/Backup.83a3473b8a5941e0.js": "/js/bundle/Backup.83a3473b8a5941e0.js",
    "/js/bundle/Warehouses.83a3473b8a5941e0.js": "/js/bundle/Warehouses.83a3473b8a5941e0.js",
    "/js/bundle/System_settings.83a3473b8a5941e0.js": "/js/bundle/System_settings.83a3473b8a5941e0.js",
    "/js/bundle/payments_purchases.83a3473b8a5941e0.js": "/js/bundle/payments_purchases.83a3473b8a5941e0.js",
    "/js/bundle/payments_sales.83a3473b8a5941e0.js": "/js/bundle/payments_sales.83a3473b8a5941e0.js",
    "/js/bundle/payments_purchases_returns.83a3473b8a5941e0.js": "/js/bundle/payments_purchases_returns.83a3473b8a5941e0.js",
    "/js/bundle/payments_sales_returns.83a3473b8a5941e0.js": "/js/bundle/payments_sales_returns.83a3473b8a5941e0.js",
    "/js/bundle/report_transactions.83a3473b8a5941e0.js": "/js/bundle/report_transactions.83a3473b8a5941e0.js",
    "/js/bundle/report_sales_by_category.83a3473b8a5941e0.js": "/js/bundle/report_sales_by_category.83a3473b8a5941e0.js",
    "/js/bundle/report_sales_by_brand.83a3473b8a5941e0.js": "/js/bundle/report_sales_by_brand.83a3473b8a5941e0.js",
    "/js/bundle/profit_and_loss.83a3473b8a5941e0.js": "/js/bundle/profit_and_loss.83a3473b8a5941e0.js",
    "/js/bundle/inventory_valuation_summary.83a3473b8a5941e0.js": "/js/bundle/inventory_valuation_summary.83a3473b8a5941e0.js",
    "/js/bundle/expenses_report.83a3473b8a5941e0.js": "/js/bundle/expenses_report.83a3473b8a5941e0.js",
    "/js/bundle/deposits_report.83a3473b8a5941e0.js": "/js/bundle/deposits_report.83a3473b8a5941e0.js",
    "/js/bundle/quantity_alerts.83a3473b8a5941e0.js": "/js/bundle/quantity_alerts.83a3473b8a5941e0.js",
    "/js/bundle/warehouse_report.83a3473b8a5941e0.js": "/js/bundle/warehouse_report.83a3473b8a5941e0.js",
    "/js/bundle/sales_report.83a3473b8a5941e0.js": "/js/bundle/sales_report.83a3473b8a5941e0.js",
    "/js/bundle/product_sales_report.83a3473b8a5941e0.js": "/js/bundle/product_sales_report.83a3473b8a5941e0.js",
    "/js/bundle/purchase_report.83a3473b8a5941e0.js": "/js/bundle/purchase_report.83a3473b8a5941e0.js",
    "/js/bundle/product_purchases_report.83a3473b8a5941e0.js": "/js/bundle/product_purchases_report.83a3473b8a5941e0.js",
    "/js/bundle/customers_report.83a3473b8a5941e0.js": "/js/bundle/customers_report.83a3473b8a5941e0.js",
    "/js/bundle/detail_customer_report.83a3473b8a5941e0.js": "/js/bundle/detail_customer_report.83a3473b8a5941e0.js",
    "/js/bundle/providers_report.83a3473b8a5941e0.js": "/js/bundle/providers_report.83a3473b8a5941e0.js",
    "/js/bundle/detail_supplier_report.83a3473b8a5941e0.js": "/js/bundle/detail_supplier_report.83a3473b8a5941e0.js",
    "/js/bundle/top_selling_products.83a3473b8a5941e0.js": "/js/bundle/top_selling_products.83a3473b8a5941e0.js",
    "/js/bundle/product_report.83a3473b8a5941e0.js": "/js/bundle/product_report.83a3473b8a5941e0.js",
    "/js/bundle/detail_product_report.83a3473b8a5941e0.js": "/js/bundle/detail_product_report.83a3473b8a5941e0.js",
    "/js/bundle/top_customers.83a3473b8a5941e0.js": "/js/bundle/top_customers.83a3473b8a5941e0.js",
    "/js/bundle/stock_report.83a3473b8a5941e0.js": "/js/bundle/stock_report.83a3473b8a5941e0.js",
    "/js/bundle/detail_stock_report.83a3473b8a5941e0.js": "/js/bundle/detail_stock_report.83a3473b8a5941e0.js",
    "/js/bundle/users_report.83a3473b8a5941e0.js": "/js/bundle/users_report.83a3473b8a5941e0.js",
    "/js/bundle/detail_user_report.83a3473b8a5941e0.js": "/js/bundle/detail_user_report.83a3473b8a5941e0.js",
    "/js/bundle/report_error_logs.83a3473b8a5941e0.js": "/js/bundle/report_error_logs.83a3473b8a5941e0.js",
    "/js/bundle/profile.83a3473b8a5941e0.js": "/js/bundle/profile.83a3473b8a5941e0.js",
    "/js/bundle/pos.83a3473b8a5941e0.js": "/js/bundle/pos.83a3473b8a5941e0.js",
    "/js/bundle/pos_draft.83a3473b8a5941e0.js": "/js/bundle/pos_draft.83a3473b8a5941e0.js",
    "/js/bundle/NotFound.83a3473b8a5941e0.js": "/js/bundle/NotFound.83a3473b8a5941e0.js",
    "/js/bundle/not_authorize.83a3473b8a5941e0.js": "/js/bundle/not_authorize.83a3473b8a5941e0.js",
    "/js/bundle/largeSidebar.83a3473b8a5941e0.js": "/js/bundle/largeSidebar.83a3473b8a5941e0.js",
    "/js/bundle/customizer.83a3473b8a5941e0.js": "/js/bundle/customizer.83a3473b8a5941e0.js",
    "/js/bundle/vue-perfect-scrollbar.83a3473b8a5941e0.js": "/js/bundle/vue-perfect-scrollbar.83a3473b8a5941e0.js",
    "/js/bundle/dashboard.7cf2b609d80c4994.js": "/js/bundle/dashboard.7cf2b609d80c4994.js",
    "/js/bundle/products.7cf2b609d80c4994.js": "/js/bundle/products.7cf2b609d80c4994.js",
    "/js/bundle/index_products.7cf2b609d80c4994.js": "/js/bundle/index_products.7cf2b609d80c4994.js",
    "/js/bundle/store_product.7cf2b609d80c4994.js": "/js/bundle/store_product.7cf2b609d80c4994.js",
    "/js/bundle/edit_product.7cf2b609d80c4994.js": "/js/bundle/edit_product.7cf2b609d80c4994.js",
    "/js/bundle/detail_product.7cf2b609d80c4994.js": "/js/bundle/detail_product.7cf2b609d80c4994.js",
    "/js/bundle/opening_stock_import.7cf2b609d80c4994.js": "/js/bundle/opening_stock_import.7cf2b609d80c4994.js",
    "/js/bundle/barcode.7cf2b609d80c4994.js": "/js/bundle/barcode.7cf2b609d80c4994.js",
    "/js/bundle/count_stock.7cf2b609d80c4994.js": "/js/bundle/count_stock.7cf2b609d80c4994.js",
    "/js/bundle/Categories.7cf2b609d80c4994.js": "/js/bundle/Categories.7cf2b609d80c4994.js",
    "/js/bundle/Brands.7cf2b609d80c4994.js": "/js/bundle/Brands.7cf2b609d80c4994.js",
    "/js/bundle/units.7cf2b609d80c4994.js": "/js/bundle/units.7cf2b609d80c4994.js",
    "/js/bundle/adjustments.7cf2b609d80c4994.js": "/js/bundle/adjustments.7cf2b609d80c4994.js",
    "/js/bundle/index_adjustment.7cf2b609d80c4994.js": "/js/bundle/index_adjustment.7cf2b609d80c4994.js",
    "/js/bundle/store_adjustment.7cf2b609d80c4994.js": "/js/bundle/store_adjustment.7cf2b609d80c4994.js",
    "/js/bundle/edit_adjustment.7cf2b609d80c4994.js": "/js/bundle/edit_adjustment.7cf2b609d80c4994.js",
    "/js/bundle/transfers.7cf2b609d80c4994.js": "/js/bundle/transfers.7cf2b609d80c4994.js",
    "/js/bundle/index_transfer.7cf2b609d80c4994.js": "/js/bundle/index_transfer.7cf2b609d80c4994.js",
    "/js/bundle/store_transfer.7cf2b609d80c4994.js": "/js/bundle/store_transfer.7cf2b609d80c4994.js",
    "/js/bundle/edit_transfer.7cf2b609d80c4994.js": "/js/bundle/edit_transfer.7cf2b609d80c4994.js",
    "/js/bundle/accounts.7cf2b609d80c4994.js": "/js/bundle/accounts.7cf2b609d80c4994.js",
    "/js/bundle/projects.7cf2b609d80c4994.js": "/js/bundle/projects.7cf2b609d80c4994.js",
    "/js/bundle/index_project.7cf2b609d80c4994.js": "/js/bundle/index_project.7cf2b609d80c4994.js",
    "/js/bundle/store_project.7cf2b609d80c4994.js": "/js/bundle/store_project.7cf2b609d80c4994.js",
    "/js/bundle/edit_project.7cf2b609d80c4994.js": "/js/bundle/edit_project.7cf2b609d80c4994.js",
    "/js/bundle/tasks.7cf2b609d80c4994.js": "/js/bundle/tasks.7cf2b609d80c4994.js",
    "/js/bundle/index_task.7cf2b609d80c4994.js": "/js/bundle/index_task.7cf2b609d80c4994.js",
    "/js/bundle/store_task.7cf2b609d80c4994.js": "/js/bundle/store_task.7cf2b609d80c4994.js",
    "/js/bundle/edit_task.7cf2b609d80c4994.js": "/js/bundle/edit_task.7cf2b609d80c4994.js",
    "/js/bundle/transfer_money.7cf2b609d80c4994.js": "/js/bundle/transfer_money.7cf2b609d80c4994.js",
    "/js/bundle/expenses.7cf2b609d80c4994.js": "/js/bundle/expenses.7cf2b609d80c4994.js",
    "/js/bundle/index_expense.7cf2b609d80c4994.js": "/js/bundle/index_expense.7cf2b609d80c4994.js",
    "/js/bundle/store_expense.7cf2b609d80c4994.js": "/js/bundle/store_expense.7cf2b609d80c4994.js",
    "/js/bundle/edit_expense.7cf2b609d80c4994.js": "/js/bundle/edit_expense.7cf2b609d80c4994.js",
    "/js/bundle/expense_category.7cf2b609d80c4994.js": "/js/bundle/expense_category.7cf2b609d80c4994.js",
    "/js/bundle/deposits.7cf2b609d80c4994.js": "/js/bundle/deposits.7cf2b609d80c4994.js",
    "/js/bundle/index_deposit.7cf2b609d80c4994.js": "/js/bundle/index_deposit.7cf2b609d80c4994.js",
    "/js/bundle/store_deposit.7cf2b609d80c4994.js": "/js/bundle/store_deposit.7cf2b609d80c4994.js",
    "/js/bundle/edit_deposit.7cf2b609d80c4994.js": "/js/bundle/edit_deposit.7cf2b609d80c4994.js",
    "/js/bundle/deposit_category.7cf2b609d80c4994.js": "/js/bundle/deposit_category.7cf2b609d80c4994.js",
    "/js/bundle/quotations.7cf2b609d80c4994.js": "/js/bundle/quotations.7cf2b609d80c4994.js",
    "/js/bundle/store_quotation.7cf2b609d80c4994.js": "/js/bundle/store_quotation.7cf2b609d80c4994.js",
    "/js/bundle/edit_quotation.7cf2b609d80c4994.js": "/js/bundle/edit_quotation.7cf2b609d80c4994.js",
    "/js/bundle/detail_quotation.7cf2b609d80c4994.js": "/js/bundle/detail_quotation.7cf2b609d80c4994.js",
    "/js/bundle/change_to_sale.7cf2b609d80c4994.js": "/js/bundle/change_to_sale.7cf2b609d80c4994.js",
    "/js/bundle/purchases.7cf2b609d80c4994.js": "/js/bundle/purchases.7cf2b609d80c4994.js",
    "/js/bundle/index_purchases.7cf2b609d80c4994.js": "/js/bundle/index_purchases.7cf2b609d80c4994.js",
    "/js/bundle/store_purchase.7cf2b609d80c4994.js": "/js/bundle/store_purchase.7cf2b609d80c4994.js",
    "/js/bundle/import_purchases.7cf2b609d80c4994.js": "/js/bundle/import_purchases.7cf2b609d80c4994.js",
    "/js/bundle/edit_purchase.7cf2b609d80c4994.js": "/js/bundle/edit_purchase.7cf2b609d80c4994.js",
    "/js/bundle/create_purchase_return.7cf2b609d80c4994.js": "/js/bundle/create_purchase_return.7cf2b609d80c4994.js",
    "/js/bundle/detail_purchase.7cf2b609d80c4994.js": "/js/bundle/detail_purchase.7cf2b609d80c4994.js",
    "/js/bundle/sales.7cf2b609d80c4994.js": "/js/bundle/sales.7cf2b609d80c4994.js",
    "/js/bundle/index_sales.7cf2b609d80c4994.js": "/js/bundle/index_sales.7cf2b609d80c4994.js",
    "/js/bundle/store_sale.7cf2b609d80c4994.js": "/js/bundle/store_sale.7cf2b609d80c4994.js",
    "/js/bundle/edit_sale.7cf2b609d80c4994.js": "/js/bundle/edit_sale.7cf2b609d80c4994.js",
    "/js/bundle/create_sale_return.7cf2b609d80c4994.js": "/js/bundle/create_sale_return.7cf2b609d80c4994.js",
    "/js/bundle/detail_sale.7cf2b609d80c4994.js": "/js/bundle/detail_sale.7cf2b609d80c4994.js",
    "/js/bundle/shipment.7cf2b609d80c4994.js": "/js/bundle/shipment.7cf2b609d80c4994.js",
    "/js/bundle/sale_return.7cf2b609d80c4994.js": "/js/bundle/sale_return.7cf2b609d80c4994.js",
    "/js/bundle/index_sale_return.7cf2b609d80c4994.js": "/js/bundle/index_sale_return.7cf2b609d80c4994.js",
    "/js/bundle/edit_sale_return.7cf2b609d80c4994.js": "/js/bundle/edit_sale_return.7cf2b609d80c4994.js",
    "/js/bundle/detail_sale_return.7cf2b609d80c4994.js": "/js/bundle/detail_sale_return.7cf2b609d80c4994.js",
    "/js/bundle/purchase_return.7cf2b609d80c4994.js": "/js/bundle/purchase_return.7cf2b609d80c4994.js",
    "/js/bundle/index_purchase_return.7cf2b609d80c4994.js": "/js/bundle/index_purchase_return.7cf2b609d80c4994.js",
    "/js/bundle/edit_purchase_return.7cf2b609d80c4994.js": "/js/bundle/edit_purchase_return.7cf2b609d80c4994.js",
    "/js/bundle/detail_purchase_return.7cf2b609d80c4994.js": "/js/bundle/detail_purchase_return.7cf2b609d80c4994.js",
    "/js/bundle/hrm.7cf2b609d80c4994.js": "/js/bundle/hrm.7cf2b609d80c4994.js",
    "/js/bundle/employees.7cf2b609d80c4994.js": "/js/bundle/employees.7cf2b609d80c4994.js",
    "/js/bundle/index_employee.7cf2b609d80c4994.js": "/js/bundle/index_employee.7cf2b609d80c4994.js",
    "/js/bundle/store_employee.7cf2b609d80c4994.js": "/js/bundle/store_employee.7cf2b609d80c4994.js",
    "/js/bundle/edit_employee.7cf2b609d80c4994.js": "/js/bundle/edit_employee.7cf2b609d80c4994.js",
    "/js/bundle/detail_employee.7cf2b609d80c4994.js": "/js/bundle/detail_employee.7cf2b609d80c4994.js",
    "/js/bundle/company.7cf2b609d80c4994.js": "/js/bundle/company.7cf2b609d80c4994.js",
    "/js/bundle/departments.7cf2b609d80c4994.js": "/js/bundle/departments.7cf2b609d80c4994.js",
    "/js/bundle/designations.7cf2b609d80c4994.js": "/js/bundle/designations.7cf2b609d80c4994.js",
    "/js/bundle/office_shift.7cf2b609d80c4994.js": "/js/bundle/office_shift.7cf2b609d80c4994.js",
    "/js/bundle/attendance.7cf2b609d80c4994.js": "/js/bundle/attendance.7cf2b609d80c4994.js",
    "/js/bundle/holidays.7cf2b609d80c4994.js": "/js/bundle/holidays.7cf2b609d80c4994.js",
    "/js/bundle/payrolls.7cf2b609d80c4994.js": "/js/bundle/payrolls.7cf2b609d80c4994.js",
    "/js/bundle/leaves.7cf2b609d80c4994.js": "/js/bundle/leaves.7cf2b609d80c4994.js",
    "/js/bundle/leave_list.7cf2b609d80c4994.js": "/js/bundle/leave_list.7cf2b609d80c4994.js",
    "/js/bundle/leave_type.7cf2b609d80c4994.js": "/js/bundle/leave_type.7cf2b609d80c4994.js",
    "/js/bundle/People.7cf2b609d80c4994.js": "/js/bundle/People.7cf2b609d80c4994.js",
    "/js/bundle/Customers.7cf2b609d80c4994.js": "/js/bundle/Customers.7cf2b609d80c4994.js",
    "/js/bundle/Customers_without_ecommerce.7cf2b609d80c4994.js": "/js/bundle/Customers_without_ecommerce.7cf2b609d80c4994.js",
    "/js/bundle/Suppliers.7cf2b609d80c4994.js": "/js/bundle/Suppliers.7cf2b609d80c4994.js",
    "/js/bundle/Users.7cf2b609d80c4994.js": "/js/bundle/Users.7cf2b609d80c4994.js",
    "/js/bundle/subscription_product.7cf2b609d80c4994.js": "/js/bundle/subscription_product.7cf2b609d80c4994.js",
    "/js/bundle/subscription_product_create.7cf2b609d80c4994.js": "/js/bundle/subscription_product_create.7cf2b609d80c4994.js",
    "/js/bundle/subscription_product_details.7cf2b609d80c4994.js": "/js/bundle/subscription_product_details.7cf2b609d80c4994.js",
    "/js/bundle/settings.7cf2b609d80c4994.js": "/js/bundle/settings.7cf2b609d80c4994.js",
    "/js/bundle/permissions.7cf2b609d80c4994.js": "/js/bundle/permissions.7cf2b609d80c4994.js",
    "/js/bundle/groupPermission.7cf2b609d80c4994.js": "/js/bundle/groupPermission.7cf2b609d80c4994.js",
    "/js/bundle/store_permission.7cf2b609d80c4994.js": "/js/bundle/store_permission.7cf2b609d80c4994.js",
    "/js/bundle/edit_permission.7cf2b609d80c4994.js": "/js/bundle/edit_permission.7cf2b609d80c4994.js",
    "/js/bundle/payment_methods.7cf2b609d80c4994.js": "/js/bundle/payment_methods.7cf2b609d80c4994.js",
    "/js/bundle/sms_settings.7cf2b609d80c4994.js": "/js/bundle/sms_settings.7cf2b609d80c4994.js",
    "/js/bundle/sms_templates.7cf2b609d80c4994.js": "/js/bundle/sms_templates.7cf2b609d80c4994.js",
    "/js/bundle/email_templates.7cf2b609d80c4994.js": "/js/bundle/email_templates.7cf2b609d80c4994.js",
    "/js/bundle/appearance_settings.7cf2b609d80c4994.js": "/js/bundle/appearance_settings.7cf2b609d80c4994.js",
    "/js/bundle/translations_settings.7cf2b609d80c4994.js": "/js/bundle/translations_settings.7cf2b609d80c4994.js",
    "/js/bundle/translations_view.7cf2b609d80c4994.js": "/js/bundle/translations_view.7cf2b609d80c4994.js",
    "/js/bundle/pos_settings.7cf2b609d80c4994.js": "/js/bundle/pos_settings.7cf2b609d80c4994.js",
    "/js/bundle/payment_gateway.7cf2b609d80c4994.js": "/js/bundle/payment_gateway.7cf2b609d80c4994.js",
    "/js/bundle/mail_settings.7cf2b609d80c4994.js": "/js/bundle/mail_settings.7cf2b609d80c4994.js",
    "/js/bundle/module_settings.7cf2b609d80c4994.js": "/js/bundle/module_settings.7cf2b609d80c4994.js",
    "/js/bundle/update_settings.7cf2b609d80c4994.js": "/js/bundle/update_settings.7cf2b609d80c4994.js",
    "/js/bundle/Currencies.7cf2b609d80c4994.js": "/js/bundle/Currencies.7cf2b609d80c4994.js",
    "/js/bundle/Backup.7cf2b609d80c4994.js": "/js/bundle/Backup.7cf2b609d80c4994.js",
    "/js/bundle/Warehouses.7cf2b609d80c4994.js": "/js/bundle/Warehouses.7cf2b609d80c4994.js",
    "/js/bundle/System_settings.7cf2b609d80c4994.js": "/js/bundle/System_settings.7cf2b609d80c4994.js",
    "/js/bundle/payments_purchases.7cf2b609d80c4994.js": "/js/bundle/payments_purchases.7cf2b609d80c4994.js",
    "/js/bundle/payments_sales.7cf2b609d80c4994.js": "/js/bundle/payments_sales.7cf2b609d80c4994.js",
    "/js/bundle/payments_purchases_returns.7cf2b609d80c4994.js": "/js/bundle/payments_purchases_returns.7cf2b609d80c4994.js",
    "/js/bundle/payments_sales_returns.7cf2b609d80c4994.js": "/js/bundle/payments_sales_returns.7cf2b609d80c4994.js",
    "/js/bundle/report_transactions.7cf2b609d80c4994.js": "/js/bundle/report_transactions.7cf2b609d80c4994.js",
    "/js/bundle/report_sales_by_category.7cf2b609d80c4994.js": "/js/bundle/report_sales_by_category.7cf2b609d80c4994.js",
    "/js/bundle/report_sales_by_brand.7cf2b609d80c4994.js": "/js/bundle/report_sales_by_brand.7cf2b609d80c4994.js",
    "/js/bundle/profit_and_loss.7cf2b609d80c4994.js": "/js/bundle/profit_and_loss.7cf2b609d80c4994.js",
    "/js/bundle/inventory_valuation_summary.7cf2b609d80c4994.js": "/js/bundle/inventory_valuation_summary.7cf2b609d80c4994.js",
    "/js/bundle/expenses_report.7cf2b609d80c4994.js": "/js/bundle/expenses_report.7cf2b609d80c4994.js",
    "/js/bundle/deposits_report.7cf2b609d80c4994.js": "/js/bundle/deposits_report.7cf2b609d80c4994.js",
    "/js/bundle/quantity_alerts.7cf2b609d80c4994.js": "/js/bundle/quantity_alerts.7cf2b609d80c4994.js",
    "/js/bundle/warehouse_report.7cf2b609d80c4994.js": "/js/bundle/warehouse_report.7cf2b609d80c4994.js",
    "/js/bundle/sales_report.7cf2b609d80c4994.js": "/js/bundle/sales_report.7cf2b609d80c4994.js",
    "/js/bundle/product_sales_report.7cf2b609d80c4994.js": "/js/bundle/product_sales_report.7cf2b609d80c4994.js",
    "/js/bundle/purchase_report.7cf2b609d80c4994.js": "/js/bundle/purchase_report.7cf2b609d80c4994.js",
    "/js/bundle/product_purchases_report.7cf2b609d80c4994.js": "/js/bundle/product_purchases_report.7cf2b609d80c4994.js",
    "/js/bundle/customers_report.7cf2b609d80c4994.js": "/js/bundle/customers_report.7cf2b609d80c4994.js",
    "/js/bundle/detail_customer_report.7cf2b609d80c4994.js": "/js/bundle/detail_customer_report.7cf2b609d80c4994.js",
    "/js/bundle/providers_report.7cf2b609d80c4994.js": "/js/bundle/providers_report.7cf2b609d80c4994.js",
    "/js/bundle/detail_supplier_report.7cf2b609d80c4994.js": "/js/bundle/detail_supplier_report.7cf2b609d80c4994.js",
    "/js/bundle/top_selling_products.7cf2b609d80c4994.js": "/js/bundle/top_selling_products.7cf2b609d80c4994.js",
    "/js/bundle/product_report.7cf2b609d80c4994.js": "/js/bundle/product_report.7cf2b609d80c4994.js",
    "/js/bundle/detail_product_report.7cf2b609d80c4994.js": "/js/bundle/detail_product_report.7cf2b609d80c4994.js",
    "/js/bundle/top_customers.7cf2b609d80c4994.js": "/js/bundle/top_customers.7cf2b609d80c4994.js",
    "/js/bundle/stock_report.7cf2b609d80c4994.js": "/js/bundle/stock_report.7cf2b609d80c4994.js",
    "/js/bundle/detail_stock_report.7cf2b609d80c4994.js": "/js/bundle/detail_stock_report.7cf2b609d80c4994.js",
    "/js/bundle/users_report.7cf2b609d80c4994.js": "/js/bundle/users_report.7cf2b609d80c4994.js",
    "/js/bundle/detail_user_report.7cf2b609d80c4994.js": "/js/bundle/detail_user_report.7cf2b609d80c4994.js",
    "/js/bundle/report_error_logs.7cf2b609d80c4994.js": "/js/bundle/report_error_logs.7cf2b609d80c4994.js",
    "/js/bundle/profile.7cf2b609d80c4994.js": "/js/bundle/profile.7cf2b609d80c4994.js",
    "/js/bundle/pos.7cf2b609d80c4994.js": "/js/bundle/pos.7cf2b609d80c4994.js",
    "/js/bundle/pos_draft.7cf2b609d80c4994.js": "/js/bundle/pos_draft.7cf2b609d80c4994.js",
    "/js/bundle/NotFound.7cf2b609d80c4994.js": "/js/bundle/NotFound.7cf2b609d80c4994.js",
    "/js/bundle/not_authorize.7cf2b609d80c4994.js": "/js/bundle/not_authorize.7cf2b609d80c4994.js",
    "/js/bundle/largeSidebar.7cf2b609d80c4994.js": "/js/bundle/largeSidebar.7cf2b609d80c4994.js",
    "/js/bundle/customizer.7cf2b609d80c4994.js": "/js/bundle/customizer.7cf2b609d80c4994.js",
    "/js/bundle/vue-perfect-scrollbar.7cf2b609d80c4994.js": "/js/bundle/vue-perfect-scrollbar.7cf2b609d80c4994.js"
}
